[
  {"name":"template X","state":{"columns":[{"name":"detail","visible":true,"width":60,"sort":{},"filters":[{}],"pinned":""},{"name":"document","visible":true,"width":30,"sort":{},"filters":[{}],"pinned":""},{"name":"comment","visible":true,"width":30,"sort":{},"filters":[{}],"pinned":""},{"name":"desk","visible":true,"width":120,"sort":{},"filters":[{}],"pinned":""},{"name":"status","visible":true,"width":100,"sort":{},"filters":[{"term":"","type":"select","selectOptions":[{"value":"","label":"all"},{"value":"reviewed","label":"reviewed"},{"value":"pending","label":"pending"}],"disableCancelFilterButton":true}],"pinned":""},{"name":"VaRLimitSize","visible":true,"width":187,"sort":{},"filters":[{}],"pinned":""},{"name":"VaRValUsage","visible":true,"width":"*","sort":{},"filters":[{}],"pinned":""},{"name":"VaRLimitUsage","visible":true,"width":"*","sort":{},"filters":[{}],"pinned":""},{"name":"VaRUnit","visible":true,"width":"*","sort":{},"filters":[{}],"pinned":""},{"name":"sVaRLimitSize","visible":true,"width":"*","sort":{},"filters":[{}],"pinned":""},{"name":"sVaRValUsage","visible":true,"width":"*","sort":{},"filters":[{}],"pinned":""},{"name":"sVaRLimitUsage","visible":true,"width":"*","sort":{},"filters":[{}],"pinned":""},{"name":"sVaRUnit","visible":true,"width":"*","sort":{},"filters":[{}],"pinned":""}],"scrollFocus":{},"selection":[],"grouping":{},"treeView":{}}},
  {"name":"template a","state":{"columns":[{"name":"detail","visible":true,"width":60,"sort":{},"filters":[{}],"pinned":""},{"name":"document","visible":true,"width":30,"sort":{},"filters":[{}],"pinned":""},{"name":"comment","visible":true,"width":30,"sort":{},"filters":[{}],"pinned":""},{"name":"desk","visible":true,"width":120,"sort":{},"filters":[{}],"pinned":""},{"name":"status","visible":true,"width":100,"sort":{},"filters":[{"term":"","type":"select","selectOptions":[{"value":"","label":"all"},{"value":"reviewed","label":"reviewed"},{"value":"pending","label":"pending"}],"disableCancelFilterButton":true}],"pinned":""},{"name":"sVaRValUsage","visible":true,"width":"*","sort":{},"filters":[{}],"pinned":""},{"name":"VaRValUsage","visible":true,"width":"*","sort":{},"filters":[{}],"pinned":""},{"name":"sVaRLimitSize","visible":true,"width":"*","sort":{},"filters":[{}],"pinned":""},{"name":"VaRLimitSize","visible":true,"width":"*","sort":{},"filters":[{}],"pinned":""},{"name":"sVaRLimitUsage","visible":true,"width":"*","sort":{},"filters":[{}],"pinned":""},{"name":"VaRUnit","visible":true,"width":"*","sort":{},"filters":[{}],"pinned":""},{"name":"sVaRUnit","visible":true,"width":"*","sort":{},"filters":[{}],"pinned":""},{"name":"VaRLimitUsage","visible":true,"width":"*","sort":{},"filters":[{}],"pinned":""}],"scrollFocus":{},"selection":[],"grouping":{},"treeView":{}}}
]